oc_assistant/__init__.py
oc_assistant/cli.py
oc_assistant/connector.py
oc_assistant/constants.py
oc_assistant/oc_api.py
oc_assistant/utils.py
oc_assistant-0.2.1.dist-info/AUTHORS.rst
oc_assistant-0.2.1.dist-info/LICENSE
oc_assistant-0.2.1.dist-info/METADATA
oc_assistant-0.2.1.dist-info/WHEEL
oc_assistant-0.2.1.dist-info/entry_points.txt
oc_assistant-0.2.1.dist-info/top_level.txt
oc_assistant-0.2.1.dist-info/RECORD
