Metadata-Version: 2.1
Name: oc-assistant
Version: 0.2.1
Summary: Python package to facilitate interaction with OC website.
Home-page: https://github.com/timoguic/oc_assistant
Author: Tim G
Author-email: timoguic@gmail.com
License: GNU General Public License v3
Keywords: oc_assistant
Platform: UNKNOWN
Classifier: Development Status :: 2 - Pre-Alpha
Classifier: Intended Audience :: Developers
Classifier: License :: OSI Approved :: GNU General Public License v3 (GPLv3)
Classifier: Natural Language :: English
Classifier: Programming Language :: Python :: 3
Classifier: Programming Language :: Python :: 3.7
Classifier: Programming Language :: Python :: 3.8
Requires-Python: >=3.7
Requires-Dist: Click (>=7.0)
Requires-Dist: python-dateutil (>=2.8)
Requires-Dist: requests (>=2.0)
